{
  "290461335": {
    "global_api_key": "ce78bea7ab275ea9b4fbd2ca13223e5feaaea",
    "email": "agussyakban7@gmail.com",
    "accountId": "4d296a26c89546519f40d16024d914df",
    "accountName": "Agussyakban7@gmail.com's Account",
    "createdAt": "2025-06-07T10:52:05.450Z",
    "lastUpdated": "2025-06-07T11:18:49.768Z"
  },
  "866930833": {
    "global_api_key": "1309950ce5f87f73ada0f5034d02b183dd572",
    "email": "dropking1122@gmail.com",
    "accountId": "542e1023ded6201b734e92ccbdde0b14",
    "accountName": "Dropking1122@gmail.com's Account",
    "createdAt": "2025-05-31T02:41:40.780Z",
    "lastUpdated": "2025-05-31T02:41:40.780Z"
  },
  "937359132": {
    "global_api_key": "18bcf2c32dd9d000e7bba7338d08b7ca60d2f",
    "email": "bup967577@gmail.com",
    "accountId": "e7403994c04dbaeadbc56f692966120e",
    "accountName": "Bup967577@gmail.com's Account",
    "createdAt": "2025-05-31T09:12:09.812Z",
    "lastUpdated": "2025-05-31T09:12:09.812Z"
  },
  "1049139698": {
    "global_api_key": "d6161f4f267c70b4adcb9bc8fcf22b0327520",
    "email": "yanuarrizkya2@gmail.com",
    "accountId": "514006d96915577338b03f47f9cd8b0a",
    "accountName": "Yanuarrizkya2@gmail.com's Account",
    "createdAt": "2025-06-07T11:55:30.589Z",
    "lastUpdated": "2025-06-07T11:55:30.589Z"
  },
  "1185252620": {
    "global_api_key": "c87dbc2d3427cf8b2790880935913c1acf453",
    "email": "naurafree@outlook.com",
    "accountId": "6c3ef7c064db4348743f583be124bb07",
    "accountName": "Naurafree@outlook.com's Account",
    "createdAt": "2025-06-03T01:58:45.265Z",
    "lastUpdated": "2025-06-03T01:58:45.265Z"
  },
  "5470863711": {
    "global_api_key": "13432c4a10ab86b33286d643a4a4f0e83a23d",
    "email": "Alfienddarkness1@gmail.com",
    "accountId": "b93de93468754eff0c8704300426e8c5",
    "accountName": "Alfienddarkness1@gmail.com's Account",
    "createdAt": "2025-05-31T02:17:52.072Z",
    "lastUpdated": "2025-05-31T02:41:04.250Z"
  },
  "6775445973": {
    "global_api_key": "8c766520c886833f863c22461ff10cfd7b272",
    "email": "marleenguillote@gmail.com",
    "accountId": "926caddfd18a159dfc2064c8ec329aee",
    "accountName": "Marleenguillote@gmail.com's Account",
    "createdAt": "2025-05-31T02:11:27.059Z",
    "lastUpdated": "2025-05-31T02:11:27.059Z"
  },
  "7509640911": {
    "global_api_key": "25f8263bebf7d631aca3f0c3b23c8ca560a77",
    "email": "aginazharmhlutpi14@gmail.com",
    "accountId": "ba82fac0559bf5b9d0af99cef5bb854b",
    "accountName": "Aginazharmhlutpi14@gmail.com's Account",
    "createdAt": "2025-05-31T02:31:43.947Z",
    "lastUpdated": "2025-05-31T02:31:43.948Z"
  },
  "6691212410": {
    "global_api_key": "25f8263bebf7d631aca3f0c3b23c8ca560a77",
    "email": "aginazharmhlutpi14@gmail.com",
    "accountId": "ba82fac0559bf5b9d0af99cef5bb854b",
    "accountName": "Aginazharmhlutpi14@gmail.com's Account",
    "createdAt": "2025-05-31T02:36:49.330Z",
    "lastUpdated": "2025-05-31T06:28:35.653Z"
  },
  "7954722354": {
    "global_api_key": "13432c4a10ab86b33286d643a4a4f0e83a23d",
    "email": "Alfienddarkness1@gmail.com",
    "accountId": "b93de93468754eff0c8704300426e8c5",
    "accountName": "Alfienddarkness1@gmail.com's Account",
    "createdAt": "2025-05-31T02:40:46.774Z",
    "lastUpdated": "2025-06-06T13:53:41.123Z"
  },
  "5588821261": {
    "global_api_key": "ebd2aa33923817f8883a0fccdef18dc2ec749",
    "email": "dprasactico@gmail.com",
    "accountId": "510e8e38de8045d85bcbf462054a07ef",
    "accountName": "Dprasactico@gmail.com's Account",
    "createdAt": "2025-05-31T03:17:04.207Z",
    "lastUpdated": "2025-05-31T03:17:04.207Z"
  },
  "7065915127": {
    "global_api_key": "2cebfe19404811fa18ce3b06f065efa695cfc",
    "email": "andyyuda28@gmail.com",
    "accountId": "9160349ae77f8ae813fb22afc5487cfb",
    "accountName": "Andyyuda28@gmail.com's Account",
    "createdAt": "2025-05-31T03:32:24.089Z",
    "lastUpdated": "2025-05-31T03:32:24.089Z"
  },
  "8011311723": {
    "global_api_key": "f1cdc045291b26c69b77b76fc0b6aecb288bf",
    "email": "dlwliu79@gmail.com",
    "accountId": "e4d38baa66408ee76262c50bb4a111c4",
    "accountName": "Dlwliu79@gmail.com's Account",
    "createdAt": "2025-05-31T04:04:46.362Z",
    "lastUpdated": "2025-05-31T04:04:46.362Z"
  },
  "6389176425": {
    "global_api_key": "f80a5b54522d5c97cd3b6a26626615cd42fe7",
    "email": "widyabakti02@gmail.com",
    "accountId": "e8c205f556e989e89cbbf38642947544",
    "accountName": "Widyabakti02@gmail.com's Account",
    "createdAt": "2025-05-31T04:44:10.034Z",
    "lastUpdated": "2025-05-31T04:44:10.034Z"
  },
  "5507027005": {
    "global_api_key": "5c0ca3d47e84d48b3abd1142c91197a06a4b8",
    "email": "wdev2121@gmail.com",
    "accountId": "702cc775dd3a5e9ce4c3564d6bb9f30d",
    "accountName": "Wdev2121@gmail.com's Account",
    "createdAt": "2025-05-31T04:53:04.204Z",
    "lastUpdated": "2025-05-31T04:53:04.204Z"
  },
  "5574443874": {
    "global_api_key": "5804677c052dbf98532a0a6684dbfd936aee0",
    "email": "babahoki777@gmail.com",
    "accountId": "8a5c5c6f71195d4ce6b0818cdeac96c6",
    "accountName": "Babahoki777@gmail.com's Account",
    "createdAt": "2025-05-31T05:49:03.839Z",
    "lastUpdated": "2025-05-31T05:49:03.839Z"
  },
  "5741324985": {
    "global_api_key": "526873e65a55a014b33e5545101eda61496fe",
    "email": "restiadi101@gmail.com",
    "accountId": "b0df6c3aa445414d26de76405cf701a4",
    "accountName": "Restiadi101@gmail.com's Account",
    "createdAt": "2025-05-31T06:04:14.416Z",
    "lastUpdated": "2025-05-31T06:04:14.417Z"
  },
  "6345820764": {
    "global_api_key": "0104fb8039c60cf4c13062741a2aad0063fb0",
    "email": "dmaniac23@gmail.com",
    "accountId": "542eecb6e9f9ab6c80a65ef45d60db6d",
    "accountName": "Dmaniac23@gmail.com's Account",
    "createdAt": "2025-05-31T06:29:45.185Z",
    "lastUpdated": "2025-05-31T06:29:45.185Z"
  },
  "7424587154": {
    "global_api_key": "a8823dcd569d085da645f6eb64bd862d3f4a0",
    "email": "ilhamyunus.a11@gmail.com",
    "accountId": "465277eb1be4267516d06c5b5f6d7c9b",
    "accountName": "Ilhamyunus.a11@gmail.com's Account",
    "createdAt": "2025-05-31T06:38:26.723Z",
    "lastUpdated": "2025-05-31T06:38:26.723Z"
  },
  "7813953089": {
    "global_api_key": "2df54abafd84f894c0c62e721db7bf6cf9322",
    "email": "irawancandra2303@gmail.com",
    "accountId": "030a1db297469c5ae261daf1df85ab0a",
    "accountName": "Irawancandra2303@gmail.com's Account",
    "createdAt": "2025-05-31T17:12:45.180Z",
    "lastUpdated": "2025-05-31T17:12:45.180Z"
  },
  "6368766361": {
    "global_api_key": "aa918e30843b38f92285d7d0251f31a960250",
    "email": "punkpang91@gmail.com",
    "accountId": "a648364194fb7e19e03ee16afd7467d2",
    "accountName": "Punkpang91@gmail.com's Account",
    "createdAt": "2025-05-31T23:23:57.624Z",
    "lastUpdated": "2025-05-31T23:23:57.624Z"
  },
  "7365059129": {
    "global_api_key": "ef29e43be6790fb73217c845d96d56085aab7",
    "email": "acidridhotv@gmail.com",
    "accountId": "08b89beee1d11b61eb80b7975e2cc155",
    "accountName": "Acidridhotv@gmail.com's Account",
    "createdAt": "2025-06-01T01:15:52.302Z",
    "lastUpdated": "2025-06-01T01:15:52.302Z"
  },
  "5938836319": {
    "global_api_key": "c66c5097515a6dc2e1083c66a673fa11e0ca7",
    "email": "tiandhey@gmail.com",
    "accountId": "3270df284f294a08b5dd5239593a81db",
    "accountName": "Tiandhey@gmail.com's Account",
    "createdAt": "2025-06-01T02:38:00.829Z",
    "lastUpdated": "2025-06-01T02:38:00.829Z"
  },
  "7424723057": {
    "global_api_key": "e902457f2a2c32f09e3e798ea576837a81a1e",
    "email": "outsuskiciaa@gmail.com",
    "accountId": "9615fcd62ae5c2bcdfedee50f8b0235a",
    "accountName": "Outsuskiciaa@gmail.com's Account",
    "createdAt": "2025-06-01T04:37:37.158Z",
    "lastUpdated": "2025-06-01T04:37:37.158Z"
  },
  "5819931050": {
    "global_api_key": "09c5b0a7fac9bcb57f2f4a193246261165436",
    "email": "storyislam501@gmail.com",
    "accountId": "dc0456ad986b3a8530c4940eb1266c6a",
    "accountName": "Storyislam501@gmail.com's Account",
    "createdAt": "2025-06-01T08:08:07.300Z",
    "lastUpdated": "2025-06-01T08:08:07.300Z"
  },
  "7778067046": {
    "global_api_key": "c537afc83d38208d898c6ca90e78c2319413e",
    "email": "azhariskandar0707@gmail.com",
    "accountId": "ce70ed7f6a2435537bb6bce29b75d2ee",
    "accountName": "Azhariskandar0707@gmail.com's Account",
    "createdAt": "2025-06-02T03:38:07.898Z",
    "lastUpdated": "2025-06-02T03:38:07.899Z"
  },
  "7891077360": {
    "global_api_key": "a27a7fb586452c949dd60e7e67b8b05365982",
    "email": "notifpremiumvpn@gmail.com",
    "accountId": "b6dfbc881930e36072861beb2be1f12d",
    "accountName": "Notifpremiumvpn@gmail.com's Account",
    "createdAt": "2025-06-02T04:01:56.201Z",
    "lastUpdated": "2025-06-02T04:01:56.201Z"
  },
  "7275025627": {
    "global_api_key": "80d915fa1ffee1c50cb6b8649e3b0d3eee18c",
    "email": "gagalvictory9@gmail.com",
    "accountId": "d94a18c60671e41854131571dc736e3f",
    "accountName": "Gagalvictory9@gmail.com's Account",
    "createdAt": "2025-06-02T07:18:32.375Z",
    "lastUpdated": "2025-06-02T07:18:32.375Z"
  },
  "8096806380": {
    "global_api_key": "9612175fa4ea969243668b1613d8d247b8bef",
    "email": "devidprasetyo09@gmail.com",
    "accountId": "566d80b583849523028276b260d83b34",
    "accountName": "Devidprasetyo09@gmail.com's Account",
    "createdAt": "2025-06-03T03:08:28.922Z",
    "lastUpdated": "2025-06-03T03:08:28.922Z"
  },
  "6751176227": {
    "global_api_key": "f64744c029f60e4bac93a6d42857c559027ac",
    "email": "ardianrio990@gmail.com",
    "accountId": "d30a5bb6342c5212dc526e01e1041113",
    "accountName": "Ardianrio990@gmail.com's Account",
    "createdAt": "2025-06-04T09:40:05.851Z",
    "lastUpdated": "2025-06-04T09:40:05.851Z"
  },
  "5472796518": {
    "global_api_key": "6afe6cbf9825cf9f653443a3e69831f8e9e27",
    "email": "anaantaka22@gmail.com",
    "accountId": "4ac51f65d7dfaeae19af12ce2d5671be",
    "accountName": "anaantaka22@gmail.com",
    "createdAt": "2025-06-04T09:48:44.232Z",
    "lastUpdated": "2025-06-04T09:48:44.232Z"
  },
  "5347438783": {
    "global_api_key": "eb029d2c4befb8108e604897c992e19605d19",
    "email": "nurodinahmad34@gmail.com",
    "accountId": "480d5d2a8be166e320cd965ff529f27d",
    "accountName": "Nurodinahmad34@gmail.com's Account",
    "createdAt": "2025-06-06T13:05:25.958Z",
    "lastUpdated": "2025-06-06T13:05:25.958Z"
  },
  "7133324410": {
    "global_api_key": "7fb9bd2abbd60d62458cbc1632b03ca65096f",
    "email": "ardidiaaan234@gmail.com",
    "accountId": "3ef60d4219934e6bbc7e9c41e0dfb670",
    "accountName": "Ardidiaaan234@gmail.com's Account",
    "createdAt": "2025-06-06T16:55:06.764Z",
    "lastUpdated": "2025-06-06T16:55:06.764Z"
  },
  "6477171367": {
    "global_api_key": "cb7c4432bc5d4cb56db68d2d6c9a2f902192f",
    "email": "elistz21@gmail.com",
    "accountId": "90163b6e5229cf76cc422b88a435ec42",
    "accountName": "Elistz21@gmail.com's Account",
    "createdAt": "2025-06-10T13:18:06.752Z",
    "lastUpdated": "2025-06-10T13:18:06.752Z"
  }
}